pyroma/__init__.py
pyroma/__main__.py
pyroma/distributiondata.py
pyroma/projectdata.py
pyroma/pypidata.py
pyroma/ratings.py
pyroma/tests.py
pyroma-5.0.1.dist-info/LICENSE.txt
pyroma-5.0.1.dist-info/METADATA
pyroma-5.0.1.dist-info/WHEEL
pyroma-5.0.1.dist-info/entry_points.txt
pyroma-5.0.1.dist-info/top_level.txt
pyroma-5.0.1.dist-info/zip-safe
pyroma-5.0.1.dist-info/RECORD
