Metadata-Version: 2.1
Name: pyroma
Version: 5.0.1
Summary: Test your project's packaging friendliness
Home-page: https://github.com/regebro/pyroma
Author: Lennart Regebro
Author-email: regebro@gmail.com
License: MIT
Project-URL: Source Code, https://github.com/regebro/pyroma
Keywords: pypi,quality,testing
Classifier: Development Status :: 5 - Production/Stable
Classifier: Intended Audience :: Developers
Classifier: License :: OSI Approved :: MIT License
Classifier: Operating System :: OS Independent
Classifier: Programming Language :: Python
Classifier: Programming Language :: Python :: 3
Classifier: Programming Language :: Python :: 3.9
Classifier: Programming Language :: Python :: 3.10
Classifier: Programming Language :: Python :: 3.11
Classifier: Programming Language :: Python :: 3.12
Classifier: Programming Language :: Python :: 3.13
Classifier: Programming Language :: Python :: 3.14
Classifier: Programming Language :: Python :: 3 :: Only
Classifier: Programming Language :: Python :: Implementation :: CPython
Classifier: Programming Language :: Python :: Implementation :: PyPy
Requires-Python: >=3.9
License-File: LICENSE.txt
Requires-Dist: build (>=0.7.0)
Requires-Dist: docutils
Requires-Dist: packaging
Requires-Dist: pygments
Requires-Dist: requests
Requires-Dist: setuptools (>=61)
Requires-Dist: trove-classifiers (>=2022.6.26)
Provides-Extra: test
Requires-Dist: pytest ; extra == 'test'
Requires-Dist: setuptools (>=60) ; extra == 'test'
Requires-Dist: zest.releaser[recommended] ; extra == 'test'
Requires-Dist: flit-core (<4,>=3.4) ; extra == 'test'
Requires-Dist: tox ; extra == 'test'
